ztdebugger/__init__.py
ztdebugger/main.py
ztdebugger-0.1.7.dist-info/LICENSE
ztdebugger-0.1.7.dist-info/METADATA
ztdebugger-0.1.7.dist-info/WHEEL
ztdebugger-0.1.7.dist-info/top_level.txt
ztdebugger-0.1.7.dist-info/RECORD
