Metadata-Version: 2.1
Name: ztdebugger
Version: 0.1.7
Summary: my custom debugger
License-File: LICENSE
Requires-Dist: rich
Requires-Dist: pysnooper
Requires-Dist: icecream
Requires-Dist: q
